regipy/__init__.py
regipy/cli.py
regipy/cli_utils.py
regipy/constants.py
regipy/exceptions.py
regipy/hive_types.py
regipy/py.typed
regipy/recovery.py
regipy/regdiff.py
regipy/registry.py
regipy/security_utils.py
regipy/structs.py
regipy/utils.py
regipy/plugins/__init__.py
regipy/plugins/plugin.py
regipy/plugins/plugin_template.py
regipy/plugins/utils.py
regipy/plugins/validated_plugins.json
regipy/plugins/validation_status.py
regipy/plugins/amcache/__init__.py
regipy/plugins/amcache/amcache.py
regipy/plugins/bcd/__init__.py
regipy/plugins/bcd/boot_entry_list.py
regipy/plugins/ntuser/__init__.py
regipy/plugins/ntuser/appkeys.py
regipy/plugins/ntuser/classes_installer.py
regipy/plugins/ntuser/comdlg32.py
regipy/plugins/ntuser/installed_programs_ntuser.py
regipy/plugins/ntuser/muicache.py
regipy/plugins/ntuser/network_drives.py
regipy/plugins/ntuser/persistence.py
regipy/plugins/ntuser/putty.py
regipy/plugins/ntuser/recentdocs.py
regipy/plugins/ntuser/runmru.py
regipy/plugins/ntuser/shellbags_ntuser.py
regipy/plugins/ntuser/sysinternals.py
regipy/plugins/ntuser/tsclient.py
regipy/plugins/ntuser/typed_paths.py
regipy/plugins/ntuser/typed_urls.py
regipy/plugins/ntuser/user_assist.py
regipy/plugins/ntuser/winrar.py
regipy/plugins/ntuser/winscp_saved_sessions.py
regipy/plugins/ntuser/word_wheel_query.py
regipy/plugins/ntuser/wsl.py
regipy/plugins/sam/__init__.py
regipy/plugins/sam/local_sid.py
regipy/plugins/sam/samparse.py
regipy/plugins/security/__init__.py
regipy/plugins/security/domain_sid.py
regipy/plugins/software/__init__.py
regipy/plugins/software/appcertdlls.py
regipy/plugins/software/appcompatflags.py
regipy/plugins/software/appinitdlls.py
regipy/plugins/software/apppaths.py
regipy/plugins/software/classes_installer.py
regipy/plugins/software/defender.py
regipy/plugins/software/disablesr.py
regipy/plugins/software/execpolicy.py
regipy/plugins/software/image_file_execution_options.py
regipy/plugins/software/installed_programs.py
regipy-6.2.0.dist-info/licenses/LICENSE
regipy-6.2.0.dist-info/METADATA
regipy-6.2.0.dist-info/WHEEL
regipy-6.2.0.dist-info/entry_points.txt
regipy-6.2.0.dist-info/top_level.txt
regipy-6.2.0.dist-info/RECORD
