Metadata-Version: 2.4
Name: regipy
Version: 6.2.0
Summary: Python Registry Parser
Author-email: "Martin G. Korman" <martin@centauri.co.il>
License: MIT
Project-URL: Homepage, https://github.com/mkorman90/regipy/
Project-URL: Repository, https://github.com/mkorman90/regipy/
Project-URL: Issues, https://github.com/mkorman90/regipy/issues
Keywords: Python,Python3,registry,windows registry,registry parser
Classifier: Development Status :: 5 - Production/Stable
Classifier: Intended Audience :: Developers
Classifier: Natural Language :: English
Classifier: License :: OSI Approved :: MIT License
Classifier: Programming Language :: Python
Classifier: Programming Language :: Python :: 3
Classifier: Programming Language :: Python :: 3.9
Classifier: Programming Language :: Python :: 3.10
Classifier: Programming Language :: Python :: 3.11
Classifier: Programming Language :: Python :: 3.12
Classifier: Programming Language :: Python :: 3.13
Classifier: Topic :: Software Development :: Libraries
Classifier: Topic :: Utilities
Requires-Python: >=3.9
License-File: LICENSE
Requires-Dist: construct>=2.10
Requires-Dist: inflection>=0.5.1
Requires-Dist: pytz
Provides-Extra: cli
Requires-Dist: click>=7.0.0; extra == "cli"
Requires-Dist: tabulate; extra == "cli"
Provides-Extra: full
Requires-Dist: click>=7.0.0; extra == "full"
Requires-Dist: tabulate; extra == "full"
Requires-Dist: libfwsi-python>=20240315; extra == "full"
Requires-Dist: libfwps-python>=20240310; extra == "full"
Provides-Extra: dev
Requires-Dist: pytest>=8.0; extra == "dev"
Requires-Dist: pytest-cov; extra == "dev"
Requires-Dist: ruff; extra == "dev"
Requires-Dist: mypy; extra == "dev"
Requires-Dist: pre-commit; extra == "dev"
Requires-Dist: tabulate; extra == "dev"
Requires-Dist: tomli; python_version < "3.11" and extra == "dev"
Dynamic: license-file
